tribler/__init__.py
tribler/run.py
tribler/core/__init__.py
tribler/core/check_os.py
tribler/core/conftest.py
tribler/core/exceptions.py
tribler/core/notifications.py
tribler/core/settings.py
tribler/core/setup.py
tribler/core/start_core.py
tribler/core/version.py
tribler/core/components/__init__.py
tribler/core/components/component.py
tribler/core/components/conftest.py
tribler/core/components/exceptions.py
tribler/core/components/session.py
tribler/core/components/content_discovery/__init__.py
tribler/core/components/content_discovery/content_discovery_component.py
tribler/core/components/content_discovery/settings.py
tribler/core/components/content_discovery/community/__init__.py
tribler/core/components/content_discovery/community/cache.py
tribler/core/components/content_discovery/community/content_discovery_community.py
tribler/core/components/content_discovery/community/payload.py
tribler/core/components/content_discovery/community/settings.py
tribler/core/components/content_discovery/community/tests/__init__.py
tribler/core/components/content_discovery/community/tests/test_content_discovery_community.py
tribler/core/components/content_discovery/restapi/__init__.py
tribler/core/components/content_discovery/restapi/schema.py
tribler/core/components/content_discovery/restapi/search_endpoint.py
tribler/core/components/content_discovery/restapi/tests/__init__.py
tribler/core/components/content_discovery/restapi/tests/test_search_endpoint.py
tribler/core/components/content_discovery/tests/__init__.py
tribler/core/components/content_discovery/tests/test_content_discovery_component.py
tribler/core/components/database/__init__.py
tribler/core/components/database/conftest.py
tribler/core/components/database/database_component.py
tribler/core/components/database/settings.py
tribler/core/components/database/category_filter/__init__.py
tribler/core/components/database/category_filter/category.conf
tribler/core/components/database/category_filter/category.py
tribler-7.13.1.dist-info/LICENSE.txt
tribler-7.13.1.dist-info/METADATA
tribler-7.13.1.dist-info/WHEEL
tribler-7.13.1.dist-info/entry_points.txt
tribler-7.13.1.dist-info/top_level.txt
tribler-7.13.1.dist-info/RECORD
