Metadata-Version: 2.1
Name: tribler
Version: 7.13.1
Summary: Privacy enhanced BitTorrent client with P2P content discovery
Home-page: https://github.com/Tribler/tribler
Author: Tribler Team
Author-email: info@tribler.org
Keywords: BitTorrent client,file sharing,peer-to-peer,P2P,TOR-like network
Classifier: Development Status :: 5 - Production/Stable
Classifier: Intended Audience :: Developers
Classifier: Intended Audience :: End Users/Desktop
Classifier: License :: OSI Approved :: GNU General Public License v3 (GPLv3)
Classifier: Programming Language :: Python :: 3
Classifier: Programming Language :: Python :: 3.8
Classifier: Programming Language :: Python :: 3.9
Classifier: Topic :: Communications :: File Sharing
Classifier: Topic :: Security :: Cryptography
Classifier: Operating System :: OS Independent
Requires-Python: >=3.8
License-File: LICENSE.txt
Requires-Dist: aiohttp ==3.9.0
Requires-Dist: aiohttp-apispec ==2.2.3
Requires-Dist: anyio ==3.7.1
Requires-Dist: chardet ==5.1.0
Requires-Dist: configobj ==5.0.8
Requires-Dist: cryptography ==42.0.5
Requires-Dist: Faker ==18.11.2
Requires-Dist: libnacl ==1.8.0
Requires-Dist: lz4 ==4.3.2
Requires-Dist: marshmallow ==3.19.0
Requires-Dist: networkx ==3.1
Requires-Dist: pony ==0.7.17
Requires-Dist: psutil ==5.9.5
Requires-Dist: pydantic ==1.10.11
Requires-Dist: PyOpenSSL ==24.0.0
Requires-Dist: pyyaml ==6.0
Requires-Dist: sentry-sdk ==1.31.0
Requires-Dist: yappi ==1.4.0
Requires-Dist: yarl ==1.9.2
Requires-Dist: bitarray ==2.7.6
Requires-Dist: pyipv8 ==2.13.0
Requires-Dist: libtorrent ==1.2.19
Requires-Dist: file-read-backwards ==3.0.0
Requires-Dist: Brotli ==1.0.9
Requires-Dist: human-readable ==1.3.2
Requires-Dist: colorlog ==6.7.0
Requires-Dist: filelock ==3.13.0
Requires-Dist: ipv8-rust-tunnels ==0.1.17
Requires-Dist: Pillow ==10.2.0
Requires-Dist: PyQt5 ==5.15.1
Requires-Dist: PyQt5-sip ==12.8.1
Requires-Dist: pyqtgraph ==0.12.3
Requires-Dist: PyQtWebEngine ==5.15.2
Requires-Dist: requests ==2.31.0
Requires-Dist: PyInstaller ==5.13.1 ; sys_platform != "darwin"
Requires-Dist: setuptools ==65.5.1 ; sys_platform == "darwin"
Requires-Dist: text-unidecode ==1.3 ; sys_platform == "darwin"
Requires-Dist: defusedxml ==0.7.1 ; sys_platform == "linux2" or sys_platform == "linux"
Requires-Dist: markupsafe ==2.0.1 ; sys_platform == "linux2" or sys_platform == "linux"
Requires-Dist: PyGObject ==3.44.1 ; sys_platform == "linux2" or sys_platform == "linux"
Provides-Extra: dev
Requires-Dist: aiohttp ==3.9.0 ; extra == 'dev'
Requires-Dist: aiohttp-apispec ==2.2.3 ; extra == 'dev'
Requires-Dist: anyio ==3.7.1 ; extra == 'dev'
Requires-Dist: chardet ==5.1.0 ; extra == 'dev'
Requires-Dist: configobj ==5.0.8 ; extra == 'dev'
Requires-Dist: cryptography ==42.0.5 ; extra == 'dev'
Requires-Dist: Faker ==18.11.2 ; extra == 'dev'
Requires-Dist: libnacl ==1.8.0 ; extra == 'dev'
Requires-Dist: lz4 ==4.3.2 ; extra == 'dev'
Requires-Dist: marshmallow ==3.19.0 ; extra == 'dev'
Requires-Dist: networkx ==3.1 ; extra == 'dev'
Requires-Dist: pony ==0.7.17 ; extra == 'dev'
Requires-Dist: psutil ==5.9.5 ; extra == 'dev'
Requires-Dist: pydantic ==1.10.11 ; extra == 'dev'
Requires-Dist: PyOpenSSL ==24.0.0 ; extra == 'dev'
Requires-Dist: pyyaml ==6.0 ; extra == 'dev'
Requires-Dist: sentry-sdk ==1.31.0 ; extra == 'dev'
Requires-Dist: yappi ==1.4.0 ; extra == 'dev'
Requires-Dist: yarl ==1.9.2 ; extra == 'dev'
Requires-Dist: bitarray ==2.7.6 ; extra == 'dev'
Requires-Dist: pyipv8 ==2.13.0 ; extra == 'dev'
Requires-Dist: libtorrent ==1.2.19 ; extra == 'dev'
Requires-Dist: file-read-backwards ==3.0.0 ; extra == 'dev'
Requires-Dist: Brotli ==1.0.9 ; extra == 'dev'
Requires-Dist: human-readable ==1.3.2 ; extra == 'dev'
Requires-Dist: colorlog ==6.7.0 ; extra == 'dev'
Requires-Dist: filelock ==3.13.0 ; extra == 'dev'
Requires-Dist: ipv8-rust-tunnels ==0.1.17 ; extra == 'dev'
Requires-Dist: Pillow ==10.2.0 ; extra == 'dev'
Requires-Dist: PyQt5 ==5.15.1 ; extra == 'dev'
Requires-Dist: PyQt5-sip ==12.8.1 ; extra == 'dev'
Requires-Dist: pyqtgraph ==0.12.3 ; extra == 'dev'
Requires-Dist: PyQtWebEngine ==5.15.2 ; extra == 'dev'
Requires-Dist: pytest ==7.4.3 ; extra == 'dev'
Requires-Dist: pytest-aiohttp ==1.0.5 ; extra == 'dev'
Requires-Dist: pytest-asyncio ==0.21.1 ; extra == 'dev'
Requires-Dist: pytest-randomly ==3.15.0 ; extra == 'dev'
Requires-Dist: pytest-timeout ==2.2.0 ; extra == 'dev'
Requires-Dist: pylint-pytest ==1.1.7 ; extra == 'dev'
Requires-Dist: coverage ==7.3.2 ; extra == 'dev'
Requires-Dist: pytest-qt ==4.2.0 ; extra == 'dev'
Requires-Dist: looptime ==0.2 ; (sys_platform != "win32") and extra == 'dev'
